CHANGES.rst
LICENSE.txt
MANIFEST.in
README.rst
setup.py
mobile_codes/__init__.py
mobile_codes/tests.py
mobile_codes.egg-info/PKG-INFO
mobile_codes.egg-info/SOURCES.txt
mobile_codes.egg-info/dependency_links.txt
mobile_codes.egg-info/top_level.txt
mobile_codes/json/countries.json
mobile_codes/json/countries.py
mobile_codes/json/countries.pyc
mobile_codes/json/mnc_operators.json
mobile_codes/json/sid_operators.json