Metadata-Version: 1.1
Name: mobile-codes
Version: 0.7
Summary: Library of ISO 3166, MCC and MNC codes
Home-page: https://github.com/andymckay/mobile-codes
Author: Andy McKay
Author-email: andym@mozilla.com
License: BSD
Platform: UNKNOWN
Classifier: Intended Audience :: Developers
Classifier: Natural Language :: English
Classifier: Operating System :: OS Independent
Classifier: Programming Language :: Python
Classifier: Programming Language :: Python :: 2
Classifier: Programming Language :: Python :: 2.6
Classifier: Programming Language :: Python :: 2.7
Classifier: Programming Language :: Python :: 3
Classifier: Programming Language :: Python :: 3.3
Classifier: Programming Language :: Python :: 3.4
